.git_archival.txt
.gitattributes
.gitignore
.gitmodules
.pre-commit-config.yaml
LICENSE
MANIFEST.in
README.md
noxfile.py
pyproject.toml
setup.cfg
.github/CONTRIBUTING.md
.github/dependabot.yml
.github/matchers/pylint.json
.github/workflows/ci.yml
src/includeigen/__init__.py
src/includeigen/_version.py
src/includeigen/py.typed
src/includeigen.egg-info/PKG-INFO
src/includeigen.egg-info/SOURCES.txt
src/includeigen.egg-info/dependency_links.txt
src/includeigen.egg-info/requires.txt
src/includeigen.egg-info/top_level.txt
src/includeigen/include/eigen/.git
src/includeigen/include/eigen/.gitignore
src/includeigen/include/eigen/.gitlab-ci.yml
src/includeigen/include/eigen/.hgeol
src/includeigen/include/eigen/CMakeLists.txt
src/includeigen/include/eigen/COPYING.APACHE
src/includeigen/include/eigen/COPYING.BSD
src/includeigen/include/eigen/COPYING.GPL
src/includeigen/include/eigen/COPYING.LGPL
src/includeigen/include/eigen/COPYING.MINPACK
src/includeigen/include/eigen/COPYING.MPL2
src/includeigen/include/eigen/COPYING.README
src/includeigen/include/eigen/CTestConfig.cmake
src/includeigen/include/eigen/CTestCustom.cmake.in
src/includeigen/include/eigen/INSTALL
src/includeigen/include/eigen/README.md
src/includeigen/include/eigen/eigen3.pc.in
src/includeigen/include/eigen/signature_of_eigen3_matrix_library
src/includeigen/include/eigen/.gitlab/issue_templates/Bug Report.md
src/includeigen/include/eigen/.gitlab/issue_templates/Feature Request.md
src/includeigen/include/eigen/.gitlab/merge_request_templates/Merge Request Template.md
src/includeigen/include/eigen/Eigen/Cholesky
src/includeigen/include/eigen/Eigen/CholmodSupport
src/includeigen/include/eigen/Eigen/Core
src/includeigen/include/eigen/Eigen/Dense
src/includeigen/include/eigen/Eigen/Eigen
src/includeigen/include/eigen/Eigen/Eigenvalues
src/includeigen/include/eigen/Eigen/Geometry
src/includeigen/include/eigen/Eigen/Householder
src/includeigen/include/eigen/Eigen/IterativeLinearSolvers
src/includeigen/include/eigen/Eigen/Jacobi
src/includeigen/include/eigen/Eigen/KLUSupport
src/includeigen/include/eigen/Eigen/LU
src/includeigen/include/eigen/Eigen/MetisSupport
