Metadata-Version: 2.1
Name: includeigen
Version: 0.1
Summary: `includeigen` can be used by Python packages that require the C++ library `Eigen`. It includes a version of `Eigen`, and a `get_include` function that returns the path to the directory of the source code.
Home-page: https://github.com/changepoints/includeigen
Author: Charles Truong
Author-email: me@email.com
License: BSD-3-Clause
Project-URL: Documentation, https://includeigen.readthedocs.io/
Project-URL: Bug Tracker, https://github.com/changepoints/includeigen/issues
Project-URL: Discussions, https://github.com/changepoints/includeigen/discussions
Project-URL: Changelog, https://github.com/changepoints/includeigen/releases
Platform: Any
Classifier: Development Status :: 1 - Planning
Classifier: Intended Audience :: Developers
Classifier: Intended Audience :: Science/Research
Classifier: License :: OSI Approved :: BSD License
Classifier: Operating System :: OS Independent
Classifier: Programming Language :: Python
Classifier: Programming Language :: Python :: 3
Classifier: Programming Language :: Python :: 3 :: Only
Classifier: Programming Language :: Python :: 3.7
Classifier: Programming Language :: Python :: 3.8
Classifier: Programming Language :: Python :: 3.9
Classifier: Programming Language :: Python :: 3.10
Classifier: Programming Language :: Python :: 3.11
Classifier: Topic :: Scientific/Engineering
Classifier: Typing :: Typed
Requires-Python: >=3.7
Provides-Extra: dev
Provides-Extra: test
License-File: LICENSE
